{"Papua New Guinea": "Pacific", "Greenland": "America", "Iceland": "Atlantic", "Canada": "America", "Algeria": "Africa", "Benin": "Africa", "Burkina Faso": "Africa", "Ghana": "Africa", "Cote d'Ivoire": "Africa", "Nigeria": "Africa", "Niger": "Africa", "Tunisia": "Africa", "Togo": "Africa", "Belgium": "Europe", "Germany": "Europe", "Estonia": "Europe", "Finland": "Europe", "United Kingdom": "Europe", "Guernsey": "Europe", "Jersey": "Europe", "Isle of Man": "Europe", "Falkland Islands": "Atlantic", "Netherlands": "Europe", "Ireland": "Europe", "Denmark": "Europe", "Faroe Islands": "Atlantic", "Luxembourg": "Europe", "Norway": "Europe", "Poland": "Europe", "Sweden": "Europe", "South Africa": "Africa", "Botswana": "Africa", "Congo (Brazzaville)": "Africa", "Congo (Kinshasa)": "Africa", "Swaziland": "Africa", "Central African Republic": "Africa", "Equatorial Guinea": "Africa", "Saint Helena": "Atlantic", "Mauritius": "Indian", "British Indian Ocean Territory": "Indian", "Cameroon": "Africa", "Zambia": "Africa", "Comoros": "Indian", "Mayotte": "Indian", "Reunion": "Indian", "Madagascar": "Indian", "Angola": "Africa", "Gabon": "Africa", "Sao Tome and Principe": "Africa", "Mozambique": "Africa", "Seychelles": "Indian", "Chad": "Africa", "Zimbabwe": "Africa", "Malawi": "Africa", "Lesotho": "Africa", "Mali": "Africa", "Gambia": "Africa", "Spain": "Atlantic", "Sierra Leone": "Africa", "Liberia": "Africa", "Morocco": "Africa", "Senegal": "Africa", "Mauritania": "Africa", "Guinea": "Africa", "Cape Verde": "Atlantic", "Ethiopia": "Africa", "Burundi": "Africa", "Somalia": "Africa", "Egypt": "Africa", "Kenya": "Africa", "Libya": "Africa", "Rwanda": "Africa", "Sudan": "Africa", "South Sudan": "Africa", "Tanzania": "Africa", "Uganda": "Africa", "Albania": "Europe", "Bulgaria": "Europe", "Cyprus": "Asia", "Croatia": "Europe", "France": "Europe", "Saint Pierre and Miquelon": "America", "Greece": "Europe", "Hungary": "Europe", "Italy": "Europe", "Slovenia": "Europe", "Czech Republic": "Europe", "Israel": "Asia", "Malta": "Europe", "Austria": "Europe", "Portugal": "Europe", "Bosnia and Herzegovina": "Europe", "Romania": "Europe", "Switzerland": "Europe", "Turkey": "Europe", "Moldova": "Europe", "Macedonia": "Europe", "Gibraltar": "Europe", "Serbia": "Europe", "Montenegro": "Europe", "Slovakia": "Europe", "Turks and Caicos Islands": "America", "Dominican Republic": "America", "Guatemala": "America", "Honduras": "America", "Jamaica": "America", "Mexico": "America", "Nicaragua": "America", "Panama": "America", "Costa Rica": "America", "El Salvador": "America", "Haiti": "America", "Cuba": "America", "Cayman Islands": "America", "Bahamas": "America", "Belize": "America", "Cook Islands": "Pacific", "Fiji": "Pacific", "Tonga": "Pacific", "Kiribati": "Pacific", "Wallis and Futuna": "Pacific", "Samoa": "Pacific", "American Samoa": "Pacific", "French Polynesia": "Pacific", "Vanuatu": "Pacific", "New Caledonia": "Pacific", "New Zealand": "Pacific", "Afghanistan": "Asia", "Bahrain": "Asia", "Saudi Arabia": "Asia", "Iran": "Asia", "Jordan": "Asia", "Kuwait": "Asia", "Lebanon": "Asia", "United Arab Emirates": "Asia", "Oman": "Asia", "Pakistan": "Asia", "Iraq": "Asia", "Syria": "Asia", "Qatar": "Asia", "Northern Mariana Islands": "Pacific", "Guam": "Pacific", "Marshall Islands": "Pacific", "Midway Islands": "Pacific", "Micronesia": "Pacific", "Palau": "Pacific", "Taiwan": "Asia", "Japan": "Asia", "South Korea": "Asia", "Philippines": "Asia", "Argentina": "America", "Brazil": "America", "Chile": "America", "Antarctica": "Antarctica", "Ecuador": "America", "Paraguay": "America", "Colombia": "America", "Bolivia": "America", "Suriname": "America", "French Guiana": "America", "Peru": "America", "Uruguay": "America", "Venezuela": "America", "Guyana": "America", "Antigua and Barbuda": "America", "Barbados": "America", "Dominica": "America", "Martinique": "America", "Guadeloupe": "America", "Grenada": "America", "Virgin Islands": "America", "Puerto Rico": "America", "Saint Kitts and Nevis": "America", "Saint Lucia": "America", "Aruba": "America", "Netherlands Antilles": "America", "Anguilla": "America", "Trinidad and Tobago": "America", "British Virgin Islands": "America", "Saint Vincent and the Grenadines": "America", "Kazakhstan": "Asia", "Kyrgyzstan": "Asia", "Azerbaijan": "Asia", "Russia": "Asia", "Ukraine": "Europe", "Belarus": "Europe", "Turkmenistan": "Asia", "Tajikistan": "Asia", "Uzbekistan": "Asia", "India": "Asia", "Sri Lanka": "Asia", "Cambodia": "Asia", "Bangladesh": "Asia", "Hong Kong": "Asia", "Laos": "Asia", "Macau": "Asia", "Nepal": "Asia", "Bhutan": "Asia", "Maldives": "Indian", "Thailand": "Asia", "Vietnam": "Asia", "Burma": "Asia", "Indonesia": "Asia", "Ambon": "N", "Malaysia": "Asia", "Brunei": "Asia", "East Timor": "Asia", "Singapore": "Asia", "Australia": "Australia", "Laverton": "O", "Christmas Island": "Indian", "Norfolk Island": "Pacific", "China": "Asia", "North Korea": "Asia", "Mongolia": "Asia", "United States": "America", "Terre Haute": "A", "Latvia": "Europe", "Lithuania": "Europe", "Armenia": "Asia", "Eritrea": "Africa", "Palestine": "Asia", "Georgia": "Asia", "Yemen": "Asia", "Bermuda": "Atlantic", "Solomon Islands": "Pacific", "Nauru": "Pacific", "Tuvalu": "Pacific", "Namibia": "Africa", "Djibouti": "Africa", "Montserrat": "America", "Vardø": "E", "Johnston Atoll": "Pacific", " Sheffield": "E", "Guinea-Bissau": "Africa", "Western Sahara": "Africa", " Fogo Island": "U", " Niuafo'ou Island": "U", "Niue": "Pacific", "Cocos (Keeling) Islands": "Indian", "Myanmar": "Asia", "Wake Island": "Pacific"}